pybliotecario/__init__.py
pybliotecario/argument_parser.py
pybliotecario/core_loop.py
pybliotecario/customconf.py
pybliotecario/on_cmd_message.py
pybliotecario/on_cmdline.py
pybliotecario/pybliotecario.py
pybliotecario/backend/__init__.py
pybliotecario/backend/backend_test.py
pybliotecario/backend/basic_backend.py
pybliotecario/backend/facebook_util.py
pybliotecario/backend/telegram_util.py
pybliotecario/components/__init__.py
pybliotecario/components/arxiv_mod.py
pybliotecario/components/component_core.py
pybliotecario/components/dnd.py
pybliotecario/components/github_component.py
pybliotecario/components/ip_lookup.py
pybliotecario/components/photocol.py
pybliotecario/components/pid.py
pybliotecario/components/reactions.py
pybliotecario/components/repositories.py
pybliotecario/components/scripts.py
pybliotecario/components/stocks.py
pybliotecario/components/system.py
pybliotecario/components/twitter.py
pybliotecario/components/weather.py
pybliotecario/components/wiki.py
pybliotecario-2.4.1.dist-info/METADATA
pybliotecario-2.4.1.dist-info/WHEEL
pybliotecario-2.4.1.dist-info/entry_points.txt
pybliotecario-2.4.1.dist-info/top_level.txt
pybliotecario-2.4.1.dist-info/RECORD
